gmlsnets_tensorflow/__init__.py
gmlsnets_tensorflow/bases.py
gmlsnets_tensorflow/weightfuncs.py
gmlsnets_tensorflow-0.1.dist-info/METADATA
gmlsnets_tensorflow-0.1.dist-info/WHEEL
gmlsnets_tensorflow-0.1.dist-info/top_level.txt
gmlsnets_tensorflow-0.1.dist-info/RECORD
